git_training_wheels/__init__.py
git_training_wheels/server.py
mcp_git_training_wheels-0.1.2.dist-info/METADATA
mcp_git_training_wheels-0.1.2.dist-info/WHEEL
mcp_git_training_wheels-0.1.2.dist-info/entry_points.txt
mcp_git_training_wheels-0.1.2.dist-info/licenses/LICENSE
mcp_git_training_wheels-0.1.2.dist-info/RECORD
