Metadata-Version: 2.4
Name: mcp-git-training-wheels
Version: 0.1.2
Summary: MCP server providing a safer 'git commit' alternative
Project-URL: Homepage, https://github.com/lava/mcp-git-training-wheels
Project-URL: Issues, https://github.com/lava/mcp-git-training-wheels/issues
Author-email: Benno Evers <benno.martin.evers@gmail.com>
License: MIT
License-File: LICENSE
Keywords: git,mcp,model-context-protocol
Classifier: Development Status :: 3 - Alpha
Classifier: Intended Audience :: Developers
Classifier: License :: OSI Approved :: MIT License
Classifier: Programming Language :: Python :: 3
Classifier: Programming Language :: Python :: 3.8
Classifier: Programming Language :: Python :: 3.9
Classifier: Programming Language :: Python :: 3.10
Classifier: Programming Language :: Python :: 3.11
Classifier: Programming Language :: Python :: 3.12
Requires-Python: >=3.10
Requires-Dist: fastmcp>=0.1.0
Requires-Dist: git-revise>=0.7.0
